convert2tif/__init__.py
convert2tif/convert2tif.py
convert2tif-0.1.0.dist-info/LICENSE
convert2tif-0.1.0.dist-info/METADATA
convert2tif-0.1.0.dist-info/WHEEL
convert2tif-0.1.0.dist-info/top_level.txt
convert2tif-0.1.0.dist-info/RECORD
